MultiProcessingBenchmark/CreateDataframeClass.py
MultiProcessingBenchmark/CreatePlottingClass.py
MultiProcessingBenchmark/EntryPoint.py
MultiProcessingBenchmark/MultiProc.py
MultiProcessingBenchmark/MultiProcClass.py
MultiProcessingBenchmark/SimpleStatistics.py
MultiProcessingBenchmark/SimpleStatisticsClass.py
MultiProcessingBenchmark/__init__.py
MultiProcessingBenchmark-0.2.0.dist-info/DESCRIPTION.rst
MultiProcessingBenchmark-0.2.0.dist-info/METADATA
MultiProcessingBenchmark-0.2.0.dist-info/RECORD
MultiProcessingBenchmark-0.2.0.dist-info/WHEEL
MultiProcessingBenchmark-0.2.0.dist-info/metadata.json
MultiProcessingBenchmark-0.2.0.dist-info/top_level.txt
