Metadata-Version: 2.0
Name: MultiProcessingBenchmark
Version: 0.2.0
Summary: Benchmarking library single core vs multi core for common pandas functions
Home-page: https://github.com/srivassid/MultiProcessingBenchmark
Author: Siddharth Srivastava
Author-email: s.srivas@hotmail.com
License: MIT
Platform: UNKNOWN
